py_madvr2-1.9.1.dist-info/licenses/LICENSE
pymadvr/__init__.py
pymadvr/commands.py
pymadvr/connection_pool.py
pymadvr/consts.py
pymadvr/errors.py
pymadvr/madvr.py
pymadvr/notifications.py
pymadvr/py.typed
pymadvr/simple_pool.py
pymadvr/wol.py
py_madvr2-1.9.1.dist-info/METADATA
py_madvr2-1.9.1.dist-info/WHEEL
py_madvr2-1.9.1.dist-info/top_level.txt
py_madvr2-1.9.1.dist-info/RECORD
