Metadata-Version: 2.4
Name: py_madvr2
Version: 1.9.1
Summary: A package to control MadVR Envy over IP
Home-page: https://github.com/iloveicedgreentea/py-madvr
Author: iloveicedgreentea2
Classifier: Programming Language :: Python :: 3.12
Classifier: License :: OSI Approved :: MIT License
Classifier: Operating System :: OS Independent
License-File: LICENSE
Dynamic: author
Dynamic: classifier
Dynamic: description
Dynamic: description-content-type
Dynamic: home-page
Dynamic: license-file
Dynamic: summary
